django_olympus-0.0.7.dist-info/licenses/LICENSE
olympus/__init__.py
olympus/apps.py
olympus/base.py
olympus/management/__init__.py
olympus/management/commands/__init__.py
olympus/management/commands/push_to_es.py
olympus/tests/__init__.py
django_olympus-0.0.7.dist-info/METADATA
django_olympus-0.0.7.dist-info/WHEEL
django_olympus-0.0.7.dist-info/top_level.txt
django_olympus-0.0.7.dist-info/RECORD
