Metadata-Version: 2.4
Name: django-olympus
Version: 0.0.7
Summary: Collect data from django models into ElasticSearch
Home-page: https://github.com/surface-security/django-olympus
Author: PPB - InfoSec Engineering
Author-email: surface@paddypowerbetfair.com
License: MIT
Classifier: Development Status :: 5 - Production/Stable
Classifier: Framework :: Django
Classifier: License :: OSI Approved :: MIT License
Classifier: Intended Audience :: Developers
Classifier: Operating System :: OS Independent
Classifier: Programming Language :: Python
Classifier: Programming Language :: Python :: 3.9
Classifier: Environment :: Web Environment
Classifier: Topic :: Software Development
Requires-Python: >=3.9
License-File: LICENSE
Requires-Dist: Django<6,>=3.0
Requires-Dist: elasticsearch<=7,>=6.8
Requires-Dist: tqdm<5,>=4
Requires-Dist: django-logbasecommand<1
Dynamic: license-file
